jupyterlab_cell_diff/__init__.py
jupyterlab_cell_diff/_version.py
jupyterlab_cell_diff-0.5.1.data/data/share/jupyter/labextensions/jupyterlab-cell-diff/package.json
jupyterlab_cell_diff-0.5.1.data/data/share/jupyter/labextensions/jupyterlab-cell-diff/static/299.4e7c89254e43e86dd136.js
jupyterlab_cell_diff-0.5.1.data/data/share/jupyter/labextensions/jupyterlab-cell-diff/static/379.6c16a6ff1f487fd0beb1.js
jupyterlab_cell_diff-0.5.1.data/data/share/jupyter/labextensions/jupyterlab-cell-diff/static/383.46e6bd1f76672cecd7d6.js
jupyterlab_cell_diff-0.5.1.data/data/share/jupyter/labextensions/jupyterlab-cell-diff/static/521.0042108cf1e649980cc7.js
jupyterlab_cell_diff-0.5.1.data/data/share/jupyter/labextensions/jupyterlab-cell-diff/static/680.4e7c89254e43e86dd136.js
jupyterlab_cell_diff-0.5.1.data/data/share/jupyter/labextensions/jupyterlab-cell-diff/static/728.05baaed9ee64749bccac.js
jupyterlab_cell_diff-0.5.1.data/data/share/jupyter/labextensions/jupyterlab-cell-diff/static/747.a96c97ef4c494c0eba31.js
jupyterlab_cell_diff-0.5.1.data/data/share/jupyter/labextensions/jupyterlab-cell-diff/static/879.e893334f0a3aa0434de5.js
jupyterlab_cell_diff-0.5.1.data/data/share/jupyter/labextensions/jupyterlab-cell-diff/static/remoteEntry.8d71c3588abb716509ed.js
jupyterlab_cell_diff-0.5.1.data/data/share/jupyter/labextensions/jupyterlab-cell-diff/static/style.js
jupyterlab_cell_diff-0.5.1.data/data/share/jupyter/labextensions/jupyterlab-cell-diff/static/third-party-licenses.json
jupyterlab_cell_diff-0.5.1.data/data/share/jupyter/labextensions/jupyterlab-cell-diff/install.json
jupyterlab_cell_diff-0.5.1.dist-info/METADATA
jupyterlab_cell_diff-0.5.1.dist-info/WHEEL
jupyterlab_cell_diff-0.5.1.dist-info/licenses/LICENSE
jupyterlab_cell_diff-0.5.1.dist-info/RECORD
