Metadata-Version: 2.4
Name: jupyterlab_cell_diff
Version: 0.5.1
Summary: A JupyterLab Extension for showing cell (git) diffs.
Project-URL: Homepage, https://github.com/jupyter-ai-contrib/jupyterlab-cell-diff
Project-URL: Bug Tracker, https://github.com/jupyter-ai-contrib/jupyterlab-cell-diff/issues
Project-URL: Repository, https://github.com/jupyter-ai-contrib/jupyterlab-cell-diff.git
Author-email: Zach Sailer <zachsailer@gmail.com>
License: BSD 3-Clause License
License-File: LICENSE
Keywords: jupyter,jupyterlab,jupyterlab-extension
Classifier: Framework :: Jupyter
Classifier: Framework :: Jupyter :: JupyterLab
Classifier: Framework :: Jupyter :: JupyterLab :: 4
Classifier: Framework :: Jupyter :: JupyterLab :: Extensions
Classifier: Framework :: Jupyter :: JupyterLab :: Extensions :: Prebuilt
Classifier: License :: OSI Approved :: BSD License
Classifier: Programming Language :: Python
Classifier: Programming Language :: Python :: 3
Classifier: Programming Language :: Python :: 3.9
Classifier: Programming Language :: Python :: 3.10
Classifier: Programming Language :: Python :: 3.11
Classifier: Programming Language :: Python :: 3.12
Classifier: Programming Language :: Python :: 3.13
Requires-Python: >=3.9
Requires-Dist: jupyterlab-cell-input-footer<0.4,>=0.3.1
Requires-Dist: jupyterlab-eventlistener<0.5,>=0.4.0
